convert_ui.py
convert_ui-0.3.7.dist-info/METADATA
convert_ui-0.3.7.dist-info/WHEEL
convert_ui-0.3.7.dist-info/entry_points.txt
convert_ui-0.3.7.dist-info/RECORD
