Metadata-Version: 2.4
Name: convert_ui
Version: 0.3.7
Summary: Convert PyQt UI file to Qt corresponding py File
Author-email: Momo <shuhengwen@gmail.com>
License: MIT
Requires-Python: >=3.12
Requires-Dist: pyside6==6.9.2
Requires-Dist: rich-argparse>=1.7.1
Requires-Dist: rich>=14.1.0
